Metadata-Version: 1.1
Name: zensols.clojure
Version: 0.3
Summary: Python to Clojure Bridge using a Py4J Gateway
Home-page: https://github.com/plandes/clj-py4j
Author: Paul Landes
Author-email: landes@mailc.net
License: UNKNOWN
Download-URL: https://github.com/plandes/clj-py4j/releases/download/v0.0.3/zensols.clojure-0.3-py3-none-any.whl
Keywords: clojure,py4j,gateway
Platform: UNKNOWN
